vu_lib/__init__.py
vu_lib/ipy_lib3.py
vu_lib/version.py
vu_lib-0.1.dist-info/LICENSE
vu_lib-0.1.dist-info/METADATA
vu_lib-0.1.dist-info/WHEEL
vu_lib-0.1.dist-info/entry_points.txt
vu_lib-0.1.dist-info/top_level.txt
vu_lib-0.1.dist-info/RECORD
