Metadata-Version: 2.1
Name: vu-lib
Version: 0.1
Summary: PyPi package of the Vrije Universiteit Amsterdam ipy_lib3 module.
Home-page: https://github.com/markmelnic/VU-Lib
Author: Mark Melnic
Author-email: commerce.markmelnic@gmail.com
License: MIT
Platform: UNKNOWN
Classifier: Intended Audience :: Developers
Classifier: Natural Language :: English
Classifier: License :: OSI Approved :: MIT License
Classifier: Programming Language :: Python :: 3
Classifier: Programming Language :: Python :: 3.5
Classifier: Programming Language :: Python :: 3.6
Classifier: Programming Language :: Python :: 3.7
Classifier: Programming Language :: Python :: 3.8
Classifier: Programming Language :: Python :: 3.9
